{
  "publicPath": "/_nuxt/",
  "all": [
    "../server/index.spa.html",
    "../server/index.ssr.html",
    "07c43a0.js",
    "0bc6924.js",
    "1092bcf.js",
    "122b113.js",
    "1da6893.js",
    "2cb6e1c.js",
    "305ef14.js",
    "38b8388.js",
    "3944547.js",
    "3951663.js",
    "5d32fad.js",
    "5e2144f.js",
    "601f877.js",
    "6c3f14d.js",
    "730dc8f.js",
    "7863f60.js",
    "7ff55b6.js",
    "81cbb7d.js",
    "9070f09.js",
    "958992f.js",
    "9f459bd.js",
    "LICENSES",
    "abb3198.js",
    "b41729d.js",
    "b9dd402.js",
    "bcda489.js",
    "c2d452c.js",
    "c812139.js",
    "cc6bbcf.js",
    "d15428d.js",
    "e1b5e7d.js",
    "e26634a.js",
    "e39f0f5.js",
    "img/ETRI-logo.dc12e11.png",
    "img/atomi-logo.f37e1ff.png",
    "img/kdx-logo.899d416.png",
    "img/kisiti-logo.9e2c039.png",
    "img/kt-logo.873d1a8.png",
    "img/logo3.ba0a011.png",
    "img/mars-logo.c289a52.png",
    "img/nia-logo.c417239.png",
    "img/saltlux-logo.4536a33.png"
  ],
  "initial": [
    "9070f09.js",
    "81cbb7d.js",
    "1092bcf.js",
    "38b8388.js"
  ],
  "async": [
    "07c43a0.js",
    "0bc6924.js",
    "122b113.js",
    "1da6893.js",
    "2cb6e1c.js",
    "305ef14.js",
    "3944547.js",
    "3951663.js",
    "5d32fad.js",
    "5e2144f.js",
    "601f877.js",
    "6c3f14d.js",
    "730dc8f.js",
    "7863f60.js",
    "7ff55b6.js",
    "958992f.js",
    "9f459bd.js",
    "abb3198.js",
    "b41729d.js",
    "b9dd402.js",
    "bcda489.js",
    "c2d452c.js",
    "c812139.js",
    "cc6bbcf.js",
    "d15428d.js",
    "e1b5e7d.js",
    "e26634a.js",
    "e39f0f5.js"
  ],
  "modules": {
    "13357892": [
      22,
      14,
      8,
      28
    ],
    "18302454": [
      4
    ],
    "19707590": [
      19
    ],
    "20993964": [
      19
    ],
    "23957840": [
      4
    ],
    "30814712": [
      25
    ],
    "32970122": [
      14
    ],
    "37149210": [
      19
    ],
    "46126157": [
      4
    ],
    "49733076": [
      4
    ],
    "51021574": [
      26,
      33
    ],
    "69216937": [
      9
    ],
    "70879193": [
      15,
      13,
      35,
      36,
      39,
      38,
      41,
      43,
      37,
      42,
      40
    ],
    "72570923": [
      4
    ],
    "94535950": [
      4
    ],
    "97827098": [
      4
    ],
    "c086eb64": [
      4
    ],
    "b9fe790c": [
      4
    ],
    "502bf539": [
      19
    ],
    "1b3ae6d6": [
      4
    ],
    "25afc29c": [
      4
    ],
    "6dae71b2": [
      4
    ],
    "77915f4a": [
      9
    ],
    "121f5429": [
      4
    ],
    "9eb9ed24": [
      4
    ],
    "2424423c": [
      4
    ],
    "74ca4b42": [
      19
    ],
    "f49f4c96": [
      4
    ],
    "7d17b029": [
      4
    ],
    "548122c8": [
      4
    ],
    "7607ddcd": [
      19
    ],
    "6a7b83d1": [
      19
    ],
    "4d72f520": [
      19
    ],
    "8fafc90c": [
      19
    ],
    "c2acc92c": [
      4
    ],
    "a00d4616": [
      19
    ],
    "6c7648f9": [
      4
    ],
    "78a89a65": [
      19
    ],
    "1c95cc10": [
      4
    ],
    "63c65cb8": [
      4
    ],
    "01c5f38a": [
      4
    ],
    "0df86ddb": [
      19
    ],
    "6e34bbe6": [
      19
    ],
    "4f267833": [
      19
    ],
    "44831de7": [
      4
    ],
    "0913e860": [
      19
    ],
    "39628b90": [
      4
    ],
    "4ddb3348": [
      4
    ],
    "296809db": [
      19
    ],
    "0beac38c": [
      19
    ],
    "df6611d2": [
      19
    ],
    "9f1c6cc0": [
      19
    ],
    "6c713348": [
      19
    ],
    "0f2561aa": [
      19
    ],
    "6bd13782": [
      19
    ],
    "50701f32": [
      4
    ],
    "469235b9": [
      9
    ],
    "6c713c42": [
      9
    ],
    "463cc56f": [
      9
    ],
    "0e88b74c": [
      9
    ],
    "2d120f7c": [
      9
    ],
    "6fc504eb": [
      4
    ],
    "3834c334": [
      4
    ],
    "f663cc2e": [
      19
    ],
    "5f8c07db": [
      19
    ],
    "53131b46": [
      19
    ],
    "63817f7b": [
      19
    ],
    "5eb3d74c": [
      4
    ],
    "4897b692": [
      4
    ],
    "0c7985f3": [
      4
    ],
    "3fa3578d": [
      19
    ],
    "ac703f26": [
      19
    ],
    "2b253a20": [
      19
    ],
    "28df6549": [
      4
    ],
    "154cd1a0": [
      4
    ],
    "0bf98af2": [
      4
    ],
    "3b29af23": [
      4
    ],
    "2de4e73a": [
      4
    ],
    "3968286c": [
      19
    ],
    "b4bf1a76": [
      19
    ],
    "f14b57c2": [
      4
    ],
    "0a4e7fb2": [
      4
    ],
    "53afaba1": [
      19
    ],
    "2a48b567": [
      19
    ],
    "7b39a4a6": [
      4
    ],
    "2937b1cc": [
      4
    ],
    "66d8f6b4": [
      4
    ],
    "bef548f6": [
      19
    ],
    "62154bab": [
      19
    ],
    "096607bc": [
      4
    ],
    "15e7a7f3": [
      8
    ],
    "99fb4a8e": [
      19
    ],
    "18956f88": [
      4
    ],
    "41161ec5": [
      4
    ],
    "00c64983": [
      4
    ],
    "268e36a7": [
      4
    ],
    "0a4a4e92": [
      4
    ],
    "1525184a": [
      19
    ],
    "52b54789": [
      9
    ],
    "3e31a6ea": [
      9
    ],
    "7abcbf7a": [
      9
    ],
    "df2920f2": [
      9
    ],
    "c8d5c01c": [
      9
    ],
    "39c4760c": [
      9
    ],
    "9b4b6dcc": [
      9
    ],
    "281c2e1c": [
      9
    ],
    "2dbd1165": [
      9
    ],
    "cedea65a": [
      9
    ],
    "ac0b8386": [
      9
    ],
    "c5e7fac6": [
      9
    ],
    "39697c62": [
      9
    ],
    "44814d97": [
      9
    ],
    "6dbae0af": [
      9
    ],
    "03321c61": [
      9
    ],
    "4e6759b8": [
      9
    ],
    "78b5af94": [
      9
    ],
    "559a7fc8": [
      9
    ],
    "3285ff6e": [
      9
    ],
    "485beeba": [
      9
    ],
    "b55f8392": [
      9
    ],
    "6550ec71": [
      9
    ],
    "e86db168": [
      9
    ],
    "548d39c0": [
      9
    ],
    "094b4d6a": [
      9
    ],
    "441f1c54": [
      9
    ],
    "d6d1ed24": [
      9
    ],
    "65c94d35": [
      9
    ],
    "556d032c": [
      9
    ],
    "dc6d434a": [
      9
    ],
    "02a4f018": [
      9
    ],
    "26364d8e": [
      9
    ],
    "098df9ec": [
      9
    ],
    "25b5d4c4": [
      9
    ],
    "55ab06cc": [
      9
    ],
    "749d855c": [
      9
    ],
    "0bd7ca64": [
      9
    ],
    "17a9aa6e": [
      9
    ],
    "1ee3538b": [
      9
    ],
    "1bb7d5cd": [
      9
    ],
    "6df53dd1": [
      9
    ],
    "646576d3": [
      9
    ],
    "5f874154": [
      9
    ],
    "770d7b36": [
      9
    ],
    "6a40f170": [
      9
    ],
    "b5551820": [
      9
    ],
    "1ecc3ebd": [
      9
    ],
    "42a58100": [
      9
    ],
    "34fa5bfe": [
      9
    ],
    "95139eee": [
      9
    ],
    "3f8c5279": [
      9
    ],
    "ded57cfa": [
      9
    ],
    "5bd57767": [
      9
    ],
    "fe81d4ca": [
      9
    ],
    "6741ede9": [
      9
    ],
    "12b74b1e": [
      9
    ],
    "15f0bc08": [
      9
    ],
    "911003b8": [
      9
    ],
    "909c2490": [
      9
    ],
    "19bf1fa9": [
      9
    ],
    "115d238a": [
      9
    ],
    "9c965d56": [
      9
    ],
    "57ae29a4": [
      9
    ],
    "73d60849": [
      9
    ],
    "5ae0246e": [
      9
    ],
    "edb3baae": [
      9
    ],
    "531aaa2c": [
      9
    ],
    "3f860f5a": [
      9
    ],
    "1a5b01c1": [
      9
    ],
    "8e0c45c2": [
      9
    ],
    "e68502aa": [
      9
    ],
    "a5104118": [
      9
    ],
    "1f4a9b3d": [
      9
    ],
    "257cf359": [
      9
    ],
    "a71f4762": [
      9
    ],
    "2f6cdba7": [
      9
    ],
    "6da778a6": [
      9
    ],
    "f6508a28": [
      9
    ],
    "7675f9e6": [
      9
    ],
    "8b2ac672": [
      9
    ],
    "6ee2deb8": [
      9
    ],
    "1950eaec": [
      9
    ],
    "78be6263": [
      4
    ],
    "2cbf8897": [
      19
    ],
    "0a747e5c": [
      19
    ],
    "67f76236": [
      19
    ],
    "6a8c0fd2": [
      4
    ],
    "036c27e0": [
      19
    ],
    "087290e6": [
      19
    ],
    "222367f6": [
      19
    ],
    "31b51db6": [
      19
    ],
    "50f47b24": [
      19
    ],
    "617c031b": [
      4
    ],
    "21e24da6": [
      4
    ],
    "da18ca56": [
      19
    ],
    "9f68ae9e": [
      4
    ],
    "3117d550": [
      19
    ],
    "501e3b6c": [
      19
    ],
    "22f929dd": [
      19
    ],
    "55a9988e": [
      19
    ],
    "945218a2": [
      4
    ],
    "dd91cc8c": [
      4
    ],
    "0601f9f0": [
      4
    ],
    "a9b84770": [
      4
    ],
    "018f2721": [
      4
    ],
    "ec23b06a": [
      19
    ],
    "d293ea8e": [
      19
    ],
    "71b9d9e4": [
      4
    ],
    "4b7cca98": [
      4
    ],
    "d90f92e4": [
      4
    ],
    "051bb3da": [
      4
    ],
    "4c7ede60": [
      4
    ],
    "47ed9d73": [
      4
    ],
    "169da372": [
      4
    ],
    "6f0bf471": [
      4
    ],
    "addc2562": [
      4
    ],
    "31ca4a2b": [
      4
    ],
    "3da88ee0": [
      4
    ],
    "197693d5": [
      4
    ],
    "0f0ae2b6": [
      19
    ],
    "0587368f": [
      19
    ],
    "fb0c7378": [
      19
    ],
    "6798e2a3": [
      19
    ],
    "229d8751": [
      19
    ],
    "5fef99ab": [
      19
    ],
    "5feb0df5": [
      19
    ],
    "5339b6fa": [
      19
    ],
    "2a54ecc6": [
      19
    ],
    "ee79ca3a": [
      19
    ],
    "4075de46": [
      4
    ],
    "3ee4d468": [
      19
    ],
    "3c4f7e00": [
      4
    ],
    "6fd3190b": [
      19
    ],
    "031525bc": [
      4
    ],
    "49c6157a": [
      4
    ],
    "ff438dd6": [
      4
    ],
    "5b9bb197": [
      4
    ],
    "c8a2074c": [
      4
    ],
    "26c3cb6d": [
      4
    ],
    "5b08c711": [
      4
    ],
    "275edd50": [
      4
    ],
    "204116f2": [
      4
    ],
    "4fb7381a": [
      4
    ],
    "0f1ce6b8": [
      4
    ],
    "3606e9e6": [
      4
    ],
    "7b9d0022": [
      4
    ],
    "33f8fe79": [
      4
    ],
    "72bfa718": [
      4
    ],
    "9a5e7594": [
      4
    ],
    "b13c5ce2": [
      4
    ],
    "9b2678dc": [
      4
    ],
    "c9a4f1f0": [
      4
    ],
    "3b2bdf9b": [
      4
    ],
    "20dedc1c": [
      4
    ],
    "836961ec": [
      4
    ],
    "1cf97274": [
      4
    ],
    "df65970c": [
      19
    ],
    "9e756956": [
      19
    ],
    "7b67fec3": [
      4
    ],
    "3c13919c": [
      19
    ],
    "13e341da": [
      4
    ],
    "6197f689": [
      4
    ],
    "6f2c47da": [
      19
    ],
    "d2f368ec": [
      19
    ],
    "5ff1df86": [
      19
    ],
    "d7890da0": [
      19
    ],
    "6b9d91e1": [
      19
    ],
    "22f181b5": [
      19
    ],
    "503432b2": [
      19
    ],
    "471cb2f8": [
      19
    ],
    "250d98fa": [
      19
    ],
    "72aeab98": [
      19
    ],
    "72e01350": [
      4
    ],
    "136b0cda": [
      4
    ],
    "4e55e9ab": [
      19
    ],
    "00683296": [
      19
    ],
    "5075c576": [
      4
    ],
    "60c77471": [
      4
    ],
    "be736650": [
      4
    ],
    "204b3e43": [
      4
    ],
    "511cace4": [
      4
    ],
    "0478bae5": [
      4
    ],
    "04d49420": [
      4
    ],
    "094b540b": [
      4
    ],
    "373185ea": [
      4
    ],
    "c8f29af0": [
      4
    ],
    "65b04ec4": [
      4
    ],
    "e5212490": [
      4
    ],
    "6d6a23e3": [
      4
    ],
    "d31c7a82": [
      4
    ],
    "458a3b32": [
      4
    ],
    "6dba66db": [
      4
    ],
    "5056d67a": [
      4
    ],
    "501bf440": [
      9
    ],
    "4e2d60c7": [
      19
    ],
    "335a5d7f": [
      4
    ],
    "3f3becc8": [
      19
    ],
    "0f0e0884": [
      19
    ],
    "7d862591": [
      19
    ],
    "7e03eef7": [
      19
    ],
    "4f7af490": [
      19
    ],
    "72fc1346": [
      19
    ],
    "1c220756": [
      19
    ],
    "2750553b": [
      19
    ],
    "7781353c": [
      19
    ],
    "2d5ab053": [
      19
    ],
    "b565b7ea": [
      19
    ],
    "43dc4624": [
      19
    ],
    "17e0c9ea": [
      19
    ],
    "35e39664": [
      19
    ],
    "d72ab6fc": [
      19
    ],
    "554482f3": [
      4
    ],
    "5674e0d6": [
      19
    ],
    "93f2b212": [
      4
    ],
    "7bbb64b0": [
      4
    ],
    "10786e7a": [
      4
    ],
    "6b5d3d77": [
      4
    ],
    "6496dedd": [
      4
    ],
    "3f640c13": [
      4
    ],
    "e18a6e46": [
      4
    ],
    "22f1fdac": [
      4
    ],
    "28a10662": [
      4
    ],
    "39abaa07": [
      4
    ],
    "4828aba2": [
      4
    ],
    "2fd8edeb": [
      4
    ],
    "85a873fe": [
      9
    ],
    "0c0ce074": [
      4
    ],
    "2f873aa1": [
      4
    ],
    "7b80dae2": [
      19
    ],
    "17ff8b6d": [
      4
    ],
    "8a17efc4": [
      4
    ],
    "592f50ea": [
      4
    ],
    "0737475c": [
      4
    ],
    "11d7be54": [
      14
    ],
    "035bb82c": [
      19
    ],
    "60255f1c": [
      4
    ],
    "05a0f581": [
      4
    ],
    "641e1e18": [
      14
    ],
    "62fd7232": [
      19
    ],
    "1d5cc662": [
      19
    ],
    "3c31986e": [
      19
    ],
    "548ce97c": [
      19
    ],
    "33c3b6b6": [
      19
    ],
    "d888f308": [
      19
    ],
    "c52dc08a": [
      4
    ],
    "5cb9281a": [
      4
    ],
    "f0e7fb90": [
      19
    ],
    "5593a6e8": [
      19
    ],
    "37797ab2": [
      19
    ],
    "4ecec3f0": [
      19
    ],
    "fa2d5f4e": [
      19
    ],
    "c411d3e8": [
      19
    ],
    "6cf941f0": [
      19
    ],
    "1039ef99": [
      19
    ],
    "526ae5b4": [
      19
    ],
    "b1b8ccd2": [
      19
    ],
    "69c0d46a": [
      19
    ],
    "e58b52d2": [
      19
    ],
    "18e5bf50": [
      19
    ],
    "d9e4a936": [
      19
    ],
    "0a4ba74c": [
      19
    ],
    "12a755e0": [
      19
    ],
    "499bbd2c": [
      19
    ],
    "7bcbb532": [
      19
    ],
    "54da76f6": [
      19
    ],
    "0a0aa858": [
      9
    ],
    "7bf22070": [
      19
    ],
    "597efaff": [
      9
    ],
    "a1c3baa4": [
      9
    ],
    "06d865f1": [
      9
    ],
    "184a3161": [
      9
    ],
    "1dd73bfa": [
      9
    ],
    "0ef52bae": [
      9
    ],
    "273ce94c": [
      9
    ],
    "5a297190": [
      9
    ],
    "565df0a5": [
      9
    ],
    "613e1050": [
      9
    ],
    "5240ac9d": [
      9
    ],
    "37507c9f": [
      9
    ],
    "58d534af": [
      9
    ],
    "c44ed362": [
      4
    ],
    "224c2438": [
      4
    ],
    "67a37f5b": [
      4
    ],
    "acb864a0": [
      4
    ],
    "3466af18": [
      4
    ],
    "ff55c050": [
      4
    ],
    "589fe8f2": [
      4
    ],
    "3b87acd2": [
      4
    ],
    "56352ac4": [
      4
    ],
    "c9c47d3e": [
      4
    ],
    "64d4ac3e": [
      4
    ],
    "f08b28dc": [
      4
    ],
    "ad1eeaee": [
      19
    ],
    "3c50beb6": [
      19
    ],
    "073064fa": [
      19
    ],
    "01790353": [
      19
    ],
    "1a23772e": [
      19
    ],
    "c7e7fa6a": [
      19
    ],
    "5ab01580": [
      19
    ],
    "3d1ca880": [
      9
    ],
    "1815455a": [
      9
    ],
    "230cfe02": [
      9
    ],
    "5cd77a86": [
      9
    ],
    "c2b617d0": [
      9
    ],
    "6ce8da7d": [
      9
    ],
    "30c9d480": [
      4
    ],
    "51f225c6": [
      19
    ],
    "5be18618": [
      4
    ],
    "f7bc89dc": [
      4
    ],
    "74e2fbb0": [
      4
    ],
    "30ca480e": [
      4
    ],
    "5d1b93db": [
      4
    ],
    "11081bfb": [
      4
    ],
    "516754f2": [
      9
    ],
    "50020c9c": [
      4
    ],
    "2cb29e8a": [
      19
    ],
    "17637a58": [
      19
    ],
    "124c47cd": [
      19
    ],
    "0c660ade": [
      19
    ],
    "ddaac386": [
      19
    ],
    "ad6adea8": [
      19
    ],
    "688036b0": [
      19
    ],
    "5005af62": [
      19
    ],
    "5961abe7": [
      4
    ],
    "18318b4a": [
      4
    ],
    "874af776": [
      9
    ],
    "7ab039b0": [
      9
    ],
    "330c8761": [
      19
    ],
    "3ccec374": [
      19
    ],
    "0fd4d39f": [
      19
    ],
    "0e8c6196": [
      19
    ],
    "08f24057": [
      19
    ],
    "614401ee": [
      19
    ],
    "13a919f7": [
      19
    ],
    "45a85579": [
      19
    ],
    "8bde6814": [
      19
    ],
    "1db439de": [
      19
    ],
    "51fc2f76": [
      19
    ],
    "3caefafc": [
      19
    ],
    "b9c367ba": [
      19
    ],
    "0aa7e7ce": [
      19
    ],
    "19afb96c": [
      19
    ],
    "54399b58": [
      19
    ],
    "23f353cc": [
      19
    ],
    "5f6323de": [
      19
    ],
    "25c21dfc": [
      19
    ],
    "739b34f8": [
      19
    ],
    "227df6f8": [
      19
    ],
    "f5384736": [
      9
    ],
    "7fba9918": [
      9
    ],
    "2c50507e": [
      19
    ],
    "103c3472": [
      19
    ],
    "b53b298a": [
      4
    ],
    "78b23dd0": [
      4
    ],
    "82246a9c": [
      19
    ],
    "127a2638": [
      19
    ],
    "032def92": [
      4
    ],
    "60a4ae42": [
      19
    ],
    "221755cd": [
      19
    ],
    "c570f7a2": [
      4
    ],
    "c561c668": [
      4
    ],
    "904a91ba": [
      9
    ],
    "2d3d0a3e": [
      9
    ],
    "7bfe2e9b": [
      4
    ],
    "5ef0d178": [
      4
    ],
    "6b49c6db": [
      4
    ],
    "ece38690": [
      4
    ],
    "43f3bb1b": [
      4
    ],
    "54efa778": [
      4
    ],
    "2df2415b": [
      4
    ],
    "10e4e438": [
      4
    ],
    "125f5cc2": [
      4
    ],
    "35ea2dbc": [
      4
    ],
    "7f148b95": [
      4
    ],
    "40c6d4b2": [
      4
    ],
    "6e574d62": [
      4
    ],
    "69a5cf3d": [
      4
    ],
    "69ad67da": [
      4
    ],
    "7f6db66a": [
      4
    ],
    "9dc2f730": [
      4
    ],
    "4b21edf8": [
      4
    ],
    "0cd43715": [
      4
    ],
    "7b1246dd": [
      19
    ],
    "c37e6a16": [
      4
    ],
    "a67b2b90": [
      4
    ],
    "7563d715": [
      4
    ],
    "663936b2": [
      4
    ],
    "2ad91a4e": [
      4
    ],
    "c120165e": [
      4
    ],
    "1c3ff57e": [
      4
    ],
    "32afe644": [
      4
    ],
    "df3b408a": [
      4
    ],
    "698e9f18": [
      4
    ],
    "d0e2648a": [
      4
    ],
    "7a817098": [
      4
    ],
    "4241e87d": [
      4
    ],
    "3d7f49cc": [
      4
    ],
    "c6df15e8": [
      9
    ],
    "029563ca": [
      9
    ],
    "54a7a6ca": [
      4
    ],
    "a24f2810": [
      4
    ],
    "3b6f0223": [
      4
    ],
    "05bd6980": [
      4
    ],
    "40754d6e": [
      4
    ],
    "5eca8e34": [
      4
    ],
    "dbb93d62": [
      9
    ],
    "095d1efb": [
      9
    ],
    "fb8e9e6c": [
      9
    ],
    "02aa2304": [
      9
    ],
    "108ca70d": [
      9
    ],
    "49972d1b": [
      4
    ],
    "67dba2f8": [
      4
    ],
    "06e83f2e": [
      9
    ],
    "be0f5d06": [
      9
    ],
    "3b1b3272": [
      9
    ],
    "4ec53816": [
      9
    ],
    "58df530a": [
      9
    ],
    "3fe327ca": [
      9
    ],
    "0f15813b": [
      4
    ],
    "21ae6bd0": [
      4
    ],
    "015f6512": [
      4
    ],
    "7dfad2d8": [
      4
    ],
    "4a370b84": [
      4
    ],
    "3797d832": [
      9
    ],
    "13d46714": [
      9
    ],
    "b107ea46": [
      9
    ],
    "705c48a8": [
      9
    ],
    "43fe7df8": [
      9
    ],
    "32d5b3ee": [
      9
    ],
    "ff48503a": [
      9
    ],
    "62d220b4": [
      9
    ],
    "a17d8620": [
      9
    ],
    "ccb4f3fe": [
      9
    ],
    "2a608c5b": [
      19
    ],
    "65d90c90": [
      4
    ],
    "14d33d7b": [
      4
    ],
    "25cf29d8": [
      4
    ],
    "617bb8bb": [
      4
    ],
    "7277a518": [
      4
    ],
    "0c10556f": [
      4
    ],
    "a9e26fe8": [
      4
    ],
    "b93f8c8a": [
      4
    ],
    "7cb6a0d0": [
      4
    ],
    "d75de61c": [
      9
    ],
    "7eb55603": [
      9
    ],
    "c832a288": [
      9
    ],
    "03e8f06a": [
      9
    ],
    "6289d64e": [
      9
    ],
    "e37a6588": [
      9
    ],
    "772f8f1e": [
      9
    ],
    "eafa596e": [
      4
    ],
    "802101ba": [
      4
    ],
    "a917ea12": [
      4
    ],
    "2cc57578": [
      4
    ],
    "17d80877": [
      9
    ],
    "3c99e6e4": [
      4
    ],
    "7b355799": [
      9
    ],
    "4621aab0": [
      4
    ],
    "44c3d86a": [
      4
    ],
    "5db06456": [
      4
    ],
    "fadb6546": [
      4
    ],
    "4adc12ef": [
      4
    ],
    "bdf7f44e": [
      4
    ],
    "8d0741f0": [
      4
    ],
    "72edbe8b": [
      4
    ],
    "5a4b2aa6": [
      4
    ],
    "514aa0fe": [
      4
    ],
    "1289b259": [
      4
    ],
    "9dd31b82": [
      9
    ],
    "ef404e9e": [
      9
    ],
    "8f9bc83a": [
      9
    ],
    "fb47323c": [
      9
    ],
    "3d5e278a": [
      19
    ],
    "136bef44": [
      19
    ],
    "601c568c": [
      19
    ],
    "c7271a76": [
      19
    ],
    "4d031364": [
      19
    ],
    "7ec41463": [
      19
    ],
    "3048d86e": [
      19
    ],
    "e7faf68e": [
      19
    ],
    "0ad9c58c": [
      19
    ],
    "2a278385": [
      19
    ],
    "b1b4ba9a": [
      19
    ],
    "5d42b3d2": [
      19
    ],
    "280938d6": [
      19
    ],
    "42980f80": [
      19
    ],
    "d1772c5a": [
      19
    ],
    "50c4d12c": [
      19
    ],
    "5f5db88f": [
      9
    ],
    "7cb6c383": [
      4
    ],
    "fcb9fd3a": [
      4
    ],
    "72726d53": [
      4
    ],
    "50229c58": [
      4
    ],
    "7fe33743": [
      4
    ],
    "0b7e4843": [
      4
    ],
    "8800faba": [
      4
    ],
    "48bf4811": [
      4
    ],
    "dd979588": [
      4
    ],
    "67df3dba": [
      4
    ],
    "6cba2f9d": [
      4
    ],
    "256217f6": [
      4
    ],
    "52d1d745": [
      4
    ],
    "b18c3c7a": [
      4
    ],
    "19849d82": [
      4
    ],
    "605b64c7": [
      4
    ],
    "af00f8ba": [
      4
    ],
    "6ca89e06": [
      4
    ],
    "d2ccbe2a": [
      4
    ],
    "f79a1ce4": [
      4
    ],
    "33fe26b2": [
      14
    ],
    "87b67bbc": [
      14
    ],
    "2093a163": [
      14
    ],
    "0b4086a2": [
      27,
      12,
      14
    ],
    "1913e25e": [
      26,
      33
    ],
    "2d7e0b34": [
      2
    ],
    "3af3fa08": [
      17,
      35,
      36,
      39,
      38,
      41,
      43,
      37,
      42,
      40
    ],
    "4bb3771a": [
      16,
      10
    ],
    "113fba56": [
      34,
      12
    ],
    "4c29126e": [
      30,
      10
    ],
    "d0f6ea9e": [
      30,
      10
    ],
    "7a7c42b1": [
      8
    ],
    "78ccce76": [
      6,
      12,
      14,
      8,
      25
    ],
    "f41dedca": [
      7,
      5
    ],
    "2c74a986": [
      29,
      12,
      14
    ],
    "cc6914f6": [
      31,
      12
    ],
    "eeabffaa": [
      3,
      12,
      14
    ],
    "0157afa8": [
      24,
      32
    ],
    "284f1a04": [
      11,
      12
    ],
    "1fae8af4": [
      15,
      13,
      35,
      36,
      39,
      38,
      41,
      43,
      37,
      42,
      40
    ],
    "2771cd09": [
      13
    ],
    "38c5ab6a": [
      13
    ],
    "45ca9336": [
      13
    ],
    "d88899e2": [
      14
    ],
    "556dfc2c": [
      14
    ],
    "72706f68": [
      14
    ],
    "cda04b4a": [
      14
    ],
    "725c19b8": [
      14
    ],
    "70b9cbca": [
      27,
      12,
      14
    ],
    "be614d10": [
      27,
      12,
      14
    ],
    "6ed655eb": [
      27,
      12,
      14
    ],
    "a41f9bf0": [
      27,
      12,
      14
    ],
    "47b255fc": [
      27,
      12,
      14
    ],
    "680826cb": [
      27,
      12,
      14
    ],
    "510952c4": [
      26,
      33
    ],
    "083fe6ed": [
      26,
      33
    ],
    "8e0bd472": [
      2
    ],
    "9b6a80d0": [
      2
    ],
    "72e96a6e": [
      17,
      35,
      36,
      39,
      38,
      41,
      43,
      37,
      42,
      40
    ],
    "116049d0": [
      17,
      35,
      36,
      39,
      38,
      41,
      43,
      37,
      42,
      40
    ],
    "c27d2180": [
      16,
      10
    ],
    "0b14408f": [
      16,
      10
    ],
    "091242e3": [
      34,
      12
    ],
    "1af3fb72": [
      34,
      12
    ],
    "3cc40948": [
      30,
      10
    ],
    "392ae32d": [
      30,
      10
    ],
    "4ad3f684": [
      30,
      10
    ],
    "3cbaddcd": [
      30,
      10
    ],
    "6328038a": [
      8
    ],
    "b0cf84d0": [
      8
    ],
    "522b546b": [
      25
    ],
    "13dd9d88": [
      25
    ],
    "02c4e3de": [
      25
    ],
    "3a6c87d8": [
      25
    ],
    "395d8a82": [
      25
    ],
    "4a91c642": [
      25
    ],
    "d47586a0": [
      25
    ],
    "10fa2c50": [
      25
    ],
    "0ea4ee5b": [
      25
    ],
    "1a5dc744": [
      25
    ],
    "128def53": [
      25
    ],
    "128bc554": [
      25
    ],
    "4bd7eaa2": [
      25
    ],
    "c8735868": [
      25
    ],
    "57787c5e": [
      25
    ],
    "251a6e14": [
      25
    ],
    "5465426e": [
      6,
      12,
      14,
      8,
      25
    ],
    "7f9cb04c": [
      6,
      12,
      14,
      8,
      25
    ],
    "1017d747": [
      28
    ],
    "a1d36c38": [
      28
    ],
    "44caebb2": [
      28
    ],
    "c1665978": [
      28
    ],
    "3976bdc4": [
      22,
      14,
      8,
      28
    ],
    "c8c8d25a": [
      22,
      14,
      8,
      28
    ],
    "eda813fe": [
      5
    ],
    "282a689e": [
      5
    ],
    "109f31dd": [
      5
    ],
    "32f504a0": [
      5
    ],
    "5978bb30": [
      7,
      5
    ],
    "18cd1992": [
      7,
      5
    ],
    "1de0575a": [
      29,
      12,
      14
    ],
    "5d62a5a2": [
      29,
      12,
      14
    ],
    "c76c02d0": [
      31,
      12
    ],
    "72c1502e": [
      31,
      12
    ],
    "4d452af8": [
      3,
      12,
      14
    ],
    "8cd00772": [
      3,
      12,
      14
    ],
    "4265a239": [
      24,
      32
    ],
    "b6eb0970": [
      24,
      32
    ],
    "235207de": [
      11,
      12
    ],
    "18ac5562": [
      11,
      12
    ],
    "3681e9a2": [
      15,
      13,
      35,
      36,
      39,
      38,
      41,
      43,
      37,
      42,
      40
    ],
    "d5c9b46a": [
      12
    ],
    "7b7d7465": [
      12
    ],
    "74473d43": [
      8
    ],
    "539b9bdf": [
      28
    ],
    "d7a997d2": [
      25
    ],
    "7050969f": [
      25
    ],
    "0c69324a": [
      25
    ],
    "78c64737": [
      25
    ],
    "4ab3cc09": [
      25
    ],
    "f7e73f3e": [
      25
    ],
    "2e5aba7c": [
      25
    ],
    "3b392df0": [
      25
    ],
    "34e1d8e2": [
      25
    ],
    "7c213241": [
      25
    ],
    "6d5d8746": [
      25
    ],
    "6b043487": [
      25
    ],
    "3b5550aa": [
      25
    ],
    "527778ac": [
      25
    ],
    "1c7c9222": [
      25
    ],
    "516289cf": [
      25
    ],
    "ecc31f38": [
      25
    ],
    "6ac25db2": [
      25
    ],
    "48291e25": [
      25
    ],
    "2954359a": [
      25
    ],
    "539a7d98": [
      30,
      10
    ],
    "3015591a": [
      30,
      10
    ],
    "5491c670": [
      30,
      10
    ],
    "34d93498": [
      30,
      10
    ],
    "3b67107d": [
      30,
      10
    ],
    "6ea16454": [
      30,
      10
    ],
    "192aa937": [
      30,
      10
    ],
    "e1385068": [
      30,
      10
    ],
    "76b141b2": [
      30,
      10
    ],
    "2a9c8c5f": [
      30,
      10
    ],
    "b05c0dca": [
      27,
      12,
      14
    ],
    "6659cfcf": [
      27,
      12,
      14
    ],
    "139cc90d": [
      27,
      12,
      14
    ],
    "349db634": [
      27,
      12,
      14
    ],
    "79319b4c": [
      27,
      12,
      14
    ],
    "83585dba": [
      27,
      12,
      14
    ],
    "e164ec9a": [
      27,
      12,
      14
    ],
    "0679df7c": [
      26,
      33
    ],
    "52e211ef": [
      26,
      33
    ],
    "11b5222a": [
      26,
      33
    ],
    "32640d13": [
      26,
      33
    ],
    "5bbd6f00": [
      2
    ],
    "21190c10": [
      2
    ],
    "626553e2": [
      2
    ],
    "ada45a96": [
      2
    ],
    "33c78e75": [
      2
    ],
    "1c081a62": [
      17,
      35,
      36,
      39,
      38,
      41,
      43,
      37,
      42,
      40
    ],
    "1b28a9f4": [
      17,
      35,
      36,
      39,
      38,
      41,
      43,
      37,
      42,
      40
    ],
    "8f78e1b4": [
      17,
      35,
      36,
      39,
      38,
      41,
      43,
      37,
      42,
      40
    ],
    "577cea4e": [
      17,
      35,
      36,
      39,
      38,
      41,
      43,
      37,
      42,
      40
    ],
    "1328a6f3": [
      17,
      35,
      36,
      39,
      38,
      41,
      43,
      37,
      42,
      40
    ],
    "d9b2ce4a": [
      18
    ],
    "a489191e": [
      18
    ],
    "27134fe7": [
      18
    ],
    "b842a728": [
      18
    ],
    "9e3fee0c": [
      18
    ],
    "5590d1de": [
      16,
      10
    ],
    "eaea73b6": [
      16,
      10
    ],
    "66a4482a": [
      16,
      10
    ],
    "2dfaf20a": [
      16,
      10
    ],
    "25617a12": [
      16,
      10
    ],
    "716a0fe8": [
      21
    ],
    "b088197a": [
      21
    ],
    "633a32d4": [
      21
    ],
    "bc164d04": [
      21
    ],
    "17e5a6e9": [
      21
    ],
    "659cc6da": [
      34,
      12
    ],
    "6dbe1558": [
      34,
      12
    ],
    "0ac44155": [
      34,
      12
    ],
    "442250fd": [
      34,
      12
    ],
    "40c299e2": [
      34,
      12
    ],
    "6c3bba3a": [
      6,
      12,
      14,
      8,
      25
    ],
    "af2cbabc": [
      6,
      12,
      14,
      8,
      25
    ],
    "c50557b0": [
      6,
      12,
      14,
      8,
      25
    ],
    "babaee46": [
      6,
      12,
      14,
      8,
      25
    ],
    "31ffd70a": [
      6,
      12,
      14,
      8,
      25
    ],
    "8854cc6a": [
      22,
      14,
      8,
      28
    ],
    "3bb65932": [
      22,
      14,
      8,
      28
    ],
    "3819b99d": [
      22,
      14,
      8,
      28
    ],
    "2f08b48c": [
      22,
      14,
      8,
      28
    ],
    "1eef03aa": [
      22,
      14,
      8,
      28
    ],
    "ed59a142": [
      7,
      5
    ],
    "31e382db": [
      7,
      5
    ],
    "eb03316e": [
      7,
      5
    ],
    "00276940": [
      7,
      5
    ],
    "3a48d096": [
      7,
      5
    ],
    "47cc26c4": [
      29,
      12,
      14
    ],
    "4604f626": [
      29,
      12,
      14
    ],
    "555fbbf8": [
      29,
      12,
      14
    ],
    "2d15bbea": [
      29,
      12,
      14
    ],
    "5bfb1cd1": [
      29,
      12,
      14
    ],
    "315f9fc9": [
      31,
      12
    ],
    "b525e596": [
      31,
      12
    ],
    "ca0f5e8e": [
      31,
      12
    ],
    "c8df73a0": [
      31,
      12
    ],
    "24c509cc": [
      31,
      12
    ],
    "c14f6e3c": [
      3,
      12,
      14
    ],
    "488c6ae5": [
      3,
      12,
      14
    ],
    "307404b4": [
      3,
      12,
      14
    ],
    "2806d26c": [
      3,
      12,
      14
    ],
    "6e70f873": [
      3,
      12,
      14
    ],
    "8974972c": [
      24,
      32
    ],
    "2e070298": [
      24,
      32
    ],
    "a1d50044": [
      24,
      32
    ],
    "35e05fd9": [
      24,
      32
    ],
    "d42a6c2a": [
      24,
      32
    ],
    "3a4230f2": [
      11,
      12
    ],
    "48dec7aa": [
      11,
      12
    ],
    "58392fb0": [
      11,
      12
    ],
    "3f0200a5": [
      11,
      12
    ],
    "3bf42e7a": [
      11,
      12
    ],
    "65d17be8": [
      15,
      13,
      35,
      36,
      39,
      38,
      41,
      43,
      37,
      42,
      40
    ],
    "f39cd544": [
      15,
      13,
      35,
      36,
      39,
      38,
      41,
      43,
      37,
      42,
      40
    ],
    "8f5415c0": [
      15,
      13,
      35,
      36,
      39,
      38,
      41,
      43,
      37,
      42,
      40
    ],
    "35676b83": [
      15,
      13,
      35,
      36,
      39,
      38,
      41,
      43,
      37,
      42,
      40
    ],
    "f56ec7a6": [
      15,
      13,
      35,
      36,
      39,
      38,
      41,
      43,
      37,
      42,
      40
    ],
    "55f59cd7": [
      14
    ],
    "91aa4612": [
      14
    ],
    "2718e759": [
      14
    ],
    "08083ac3": [
      14
    ],
    "5dad146e": [
      5
    ],
    "3fe067bf": [
      5
    ],
    "65217b0b": [
      5
    ],
    "1208f08f": [
      28
    ],
    "e1614c22": [
      28
    ],
    "9e947708": [
      28
    ],
    "302f0448": [
      28
    ]
  },
  "assetsMapping": {
    "88581950": [
      "0bc6924.js"
    ],
    "efd8be72": [
      "07c43a0.js"
    ],
    "7ea24c87": [
      "1092bcf.js"
    ],
    "5d5dec12": [
      "122b113.js"
    ],
    "6e389ae4": [
      "1da6893.js"
    ],
    "01a8fe4a": [
      "2cb6e1c.js"
    ],
    "59d85360": [
      "305ef14.js"
    ],
    "1a3ae26b": [
      "38b8388.js"
    ],
    "45a2a32b": [
      "3944547.js"
    ],
    "dbb87ae8": [
      "3951663.js"
    ],
    "b413cbde": [
      "5d32fad.js"
    ],
    "f45ff1a6": [
      "5e2144f.js"
    ],
    "6c9e7d70": [
      "601f877.js"
    ],
    "2a130dde": [
      "6c3f14d.js"
    ],
    "b65f4b58": [
      "730dc8f.js"
    ],
    "7a60784b": [
      "7863f60.js"
    ],
    "0ff294af": [
      "7ff55b6.js"
    ],
    "085a35c4": [
      "81cbb7d.js"
    ],
    "6fca0322": [
      "9070f09.js"
    ],
    "ee29bbb4": [
      "958992f.js"
    ],
    "2f3c2c47": [
      "9f459bd.js"
    ],
    "0e5b0e60": [
      "abb3198.js"
    ],
    "3b6f4cf2": [
      "b41729d.js"
    ],
    "63c15e2b": [
      "b9dd402.js"
    ],
    "ce4a41de": [
      "bcda489.js"
    ],
    "0e23de63": [
      "c2d452c.js"
    ],
    "bbd3db8c": [
      "c812139.js"
    ],
    "537cfe94": [
      "cc6bbcf.js"
    ],
    "e7ff963a": [
      "d15428d.js"
    ],
    "257a7f08": [
      "e1b5e7d.js"
    ],
    "a3205572": [
      "e26634a.js"
    ],
    "19c9bd0f": [
      "e39f0f5.js"
    ]
  }
}